app/.streamlit/config.toml
app/__init__.py
app/app.py
app/assets/style.css
app/intersection_binary_app.py
app/intersection_multiclass_app.py
app/rashomon_binary_app.py
app/rashomon_multiclass_app.py
arsa_ml/__init__.py
arsa_ml/converters.py
arsa_ml/pipelines/__init__.py
arsa_ml/pipelines/builder_abstract.py
arsa_ml/pipelines/pipelines_from_converters.py
arsa_ml/pipelines/pipelines_user_input.py
arsa_ml/pipelines/tmp/temp_plots.pkl
arsa_ml/pipelines/tmp/temp_plots2.pkl
arsa_ml/rashomon_intersection.py
arsa_ml/rashomon_set.py
arsa_ml/visualizers/intersection_visualizer.py
arsa_ml/visualizers/rashomon_visualizer.py
arsa_ml-0.1.12.dist-info/METADATA
arsa_ml-0.1.12.dist-info/NOTICE
arsa_ml-0.1.12.dist-info/WHEEL
arsa_ml-0.1.12.dist-info/RECORD
