Metadata-Version: 2.1
Name: arsa_ml
Version: 0.1.12
Summary: ARSA_ML is a package for automated analysis of the Rashomon Set properties.
Author: Katarzyna Rogalska
Requires-Python: >=3.11,<3.13
Classifier: Programming Language :: Python :: 3
Classifier: Programming Language :: Python :: 3.11
Classifier: Programming Language :: Python :: 3.12
Requires-Dist: autogluon (>=1.4.0,<2.0.0)
Requires-Dist: h2o (==3.46.0.7)
Requires-Dist: pandas (>=2.3.2,<3.0.0)
Requires-Dist: seaborn (>=0.13.2,<0.14.0)
Requires-Dist: streamlit (>=1.51.0,<2.0.0)
Requires-Dist: tabulate (>=0.9.0,<0.10.0)
